{"cameraMode":{"drawMode":0,"name":"Shaded","section":"Shading Mode"},"sceneLighting":true,"audioPlay":false,"sceneViewState":{"m_AlwaysRefresh":false,"showFog":true,"showSkybox":true,"showFlares":true,"showImageEffects":true,"showParticleSystems":true,"showVisualEffectGraphs":true,"m_FxEnabled":true},"in2DMode":false,"pivot":{"x":742.140869140625,"y":153.80865478515626,"z":-3.83343505859375},"rotation":{"x":-0.021307045593857766,"y":-0.009900834411382676,"z":0.00021096978161949664,"w":-0.9997248649597168},"size":186.329345703125,"orthographic":false}